{"elementMetadata":{"image":"elements/provider_acton.png","notes":"my test contribution","usage":{"instanceCount":0,"customerCount":0,"traffic":0},"displayOrder":100,"active":true,"description":"Add an Act-On Instance to connect your existing Act-On account to the Marketing Hub, allowing you to manage campaigns, lists, leads etc. across multiple Marketing Elements. You will need your Act-On account information to add an instance.","eventTypes":["polling"],"hasSandboxWarnings":false,"authenticationTypes":["oauth2"],"provisioningNotes":"my test contribution","hub":"marketing","discovery":{"nativeObjectMetadataDiscovery":false,"vendorSupportCustomFieldsDiscovery":false,"supportCustomFieldsDiscovery":false,"nativeObjectDiscovery":false,"objectDiscoverySupport":false,"crudsSupported":false},"captured":false,"name":"Act-On","api":{"vendorLatestVersion":"check2","apiRateLimit":"check4","vendorDocumentationUrl":"https://www.zoho.com/crm/help/api/v2/#api-reference","vendorSupportUrl":"check4","vendorSupportWebhooks":false,"type":"unknown","version":"check"},"extendable":true,"id":34500,"bulk":{"download":true,"upload":true,"ceSupportNativeBulkUpload":false,"vendorSupportNativeBulkDownload":false,"ceSupportNativeBulkDownload":false,"vendorSupportNativeBulkUpload":false},"beta":false,"key":"acton222"},"objectMetadata":{"optout":{"fields":[{"type":"string","vendorPath":"email"},{"type":"milliseconds","vendorPath":"timestamp"},{"type":"string","vendorPath":"origin"}]},"list":{"fields":[{"custom":false,"type":"string","vendorPath":"sourceId"},{"custom":false,"type":"date","vendorPath":"tsLastCounted","mask":"milliseconds"},{"custom":false,"type":"boolean","vendorPath":"bIsSL"},{"custom":false,"type":"boolean","vendorPath":"bIsSforceReport"},{"custom":false,"type":"boolean","vendorPath":"bIsList"},{"custom":false,"type":"string","vendorPath":"description"},{"custom":false,"type":"string","vendorPath":"baseId"},{"custom":false,"type":"boolean","vendorPath":"bIsNsuiteAvailable"},{"custom":false,"type":"string","vendorPath":"sourceTS"},{"custom":false,"type":"date","vendorPath":"tsSource","mask":"milliseconds"},{"custom":false,"type":"string","vendorPath":"id"},{"custom":false,"type":"boolean","vendorPath":"bIsSforceAvailable"},{"custom":false,"type":"boolean","vendorPath":"bIsMSDynAvailable"},{"custom":false,"type":"boolean","vendorPath":"bIsSingleton"},{"custom":false,"type":"boolean","vendorPath":"bIsSforce"},{"custom":false,"type":"boolean","vendorPath":"bIsNsuite"},{"custom":false,"type":"date","vendorPath":"tsLastModified","mask":"milliseconds"},{"custom":false,"type":"boolean","vendorPath":"bIsSugar"},{"custom":false,"type":"string","vendorPath":"name"},{"custom":false,"type":"string","vendorPath":"folderName"},{"custom":false,"type":"string","vendorPath":"sourceName"},{"custom":false,"type":"string","vendorPath":"sourceSize"},{"custom":false,"type":"boolean","vendorPath":"bIsMSDyn"},{"custom":false,"type":"boolean","vendorPath":"bIsSugarAvailable"},{"custom":false,"type":"boolean","vendorPath":"bIsSLAvailable"}]},"contacts":{"fields":[{"type":"string","vendorPath":"Home Street"},{"type":"string","vendorPath":"Company"},{"type":"string","vendorPath":"First Name"},{"type":"string","vendorPath":"Middle Name"},{"type":"string","vendorPath":"Job Title"},{"type":"string","vendorPath":"Business Phone"},{"type":"string","vendorPath":"Home Country"},{"type":"string","vendorPath":"Newsletter"},{"type":"string","vendorPath":"Home Phone"},{"type":"string","vendorPath":"Last Touch"},{"type":"string","vendorPath":"Department"},{"type":"string","vendorPath":"Business City"},{"type":"string","vendorPath":"Personal Web Page"},{"type":"string","vendorPath":"EntryId"},{"type":"string","vendorPath":"Invited"},{"type":"string","vendorPath":"Home Fax"},{"type":"string","vendorPath":"Business Postal Code"},{"type":"string","vendorPath":"Business State"},{"type":"string","vendorPath":"Current Touch State"},{"type":"string","vendorPath":"Business Fax"},{"type":"string","vendorPath":"_contact_id_"},{"type":"string","vendorPath":"Home City"},{"type":"string","vendorPath":"Touch Count"},{"type":"string","vendorPath":"Attended"},{"type":"string","vendorPath":"Business Street"},{"type":"string","vendorPath":"Business Web Page"},{"type":"string","vendorPath":"Business Country"},{"type":"string","vendorPath":"Cell Phone"},{"type":"string","vendorPath":"Last Name"},{"type":"string","vendorPath":"Home State"},{"type":"string","vendorPath":"E-mail Address"},{"type":"string","vendorPath":"Home Postal Code"},{"type":"milliseconds","vendorPath":"__modified_date"},{"type":"milliseconds","vendorPath":"__created_date"}]},"subscription-categories":{"fields":[{"type":"string","vendorPath":"headername"},{"type":"string","vendorPath":"name"},{"type":"string","vendorPath":"description"},{"type":"string","vendorPath":"id"},{"type":"string","vendorPath":"headerid"}]}},"private":true,"configuration":[{"internal":true,"companyConfig":false,"displayOrder":1,"active":true,"description":"Act-On OAuth Token Revoke URL","type":"TEXTFIELD_1000","resellerConfig":false,"required":false,"hideFromConsole":true,"name":"OAuth Token Revoke URL","id":316440,"groupControl":false,"key":"oauth.token.revoke_url"},{"internal":true,"companyConfig":false,"displayOrder":1,"active":true,"description":"Act-On OAuth Token Refresh URL","type":"TEXTFIELD_1000","resellerConfig":false,"required":false,"hideFromConsole":true,"name":"OAuth Token Refresh URL","id":316439,"groupControl":false,"key":"oauth.token.refresh_url"},{"internal":true,"companyConfig":false,"displayOrder":1,"active":true,"description":"Act-On OAuth Token URL","type":"TEXTFIELD_1000","resellerConfig":false,"required":true,"hideFromConsole":true,"name":"OAuth Token URL","id":316438,"groupControl":false,"key":"oauth.token.url"},{"internal":true,"companyConfig":false,"displayOrder":1,"active":true,"description":"Act-On OAuth Authorization URL","type":"TEXTFIELD_1000","resellerConfig":false,"required":true,"hideFromConsole":true,"name":"OAuth Authorization URL","id":316437,"groupControl":false,"key":"oauth.authorization.url"},{"internal":false,"companyConfig":false,"defaultValue":"true","displayOrder":1,"active":true,"description":"Used in the token exchange API call to specify if the API credentials should be sent in the Authorization header as a Basic (base64) encoded values","type":"BOOLEAN","resellerConfig":false,"required":false,"hideFromConsole":true,"name":"OAuth Basic header","id":316436,"groupControl":false,"key":"oauth.basic.header"},{"internal":true,"companyConfig":false,"defaultValue":"3600","displayOrder":1,"active":true,"description":"Act-On OAuth Refresh Interval (s)","type":"TEXTFIELD_32","resellerConfig":false,"required":false,"hideFromConsole":true,"name":"OAuth Refresh Interval (s)","id":316435,"groupControl":false,"key":"oauth.user.refresh_interval"},{"internal":false,"companyConfig":false,"defaultValue":"200","displayOrder":1,"active":true,"description":"Max Page Size (or limit)","type":"TEXTFIELD_32","resellerConfig":false,"required":false,"hideFromConsole":true,"name":"Max Page Size (or limit)","id":316412,"groupControl":false,"key":"pagination.max"},{"internal":false,"companyConfig":false,"defaultValue":"offset","displayOrder":1,"active":true,"description":"Pagination Type","type":"TEXTFIELD_32","resellerConfig":false,"required":false,"hideFromConsole":true,"name":"Pagination Type","id":316413,"groupControl":false,"key":"pagination.type"},{"internal":false,"companyConfig":false,"defaultValue":"true","displayOrder":1,"active":true,"description":"Enables use of global fields query parameter to filter response to only specified fields. This will override any existing vendor functionality on the connector","type":"BOOLEAN","resellerConfig":false,"required":false,"hideFromConsole":true,"name":"Allow Select Fields parameter","id":316414,"groupControl":false,"key":"allow.select.fields"},{"internal":false,"companyConfig":false,"defaultValue":"https://restapi.actonsoftware.com","displayOrder":1,"active":true,"description":"Base URL","type":"TEXTFIELD_1000","resellerConfig":false,"required":false,"hideFromConsole":true,"name":"Base URL","id":316415,"groupControl":false,"key":"base.url"},{"internal":true,"companyConfig":false,"displayOrder":1,"active":true,"description":"Act-On User Access Token","type":"TEXTFIELD_128","resellerConfig":false,"required":false,"hideFromConsole":true,"name":"Act-On User Access Token","id":316416,"groupControl":false,"key":"oauth.user.token"},{"internal":true,"companyConfig":false,"displayOrder":2,"active":true,"description":"Act-On Refresh Time","type":"TEXTFIELD_128","resellerConfig":false,"required":false,"hideFromConsole":true,"name":"Act-On Refresh Time","id":316417,"groupControl":false,"key":"oauth.user.refresh_time"},{"internal":true,"companyConfig":false,"displayOrder":3,"active":true,"description":"Act-On Refresh Token","type":"TEXTFIELD_128","resellerConfig":false,"required":false,"hideFromConsole":true,"name":"Act-On Refresh token","id":316418,"groupControl":false,"key":"oauth.user.refresh_token"},{"internal":false,"companyConfig":false,"displayOrder":4,"active":true,"description":"Act-On Scope","type":"TEXTFIELD_128","resellerConfig":false,"required":false,"hideFromConsole":true,"name":"Act-On Scope","id":316419,"groupControl":false,"key":"oauth.scope"},{"internal":false,"companyConfig":false,"displayOrder":5,"active":true,"description":"Act-On Callback URL","type":"TEXTFIELD_128","resellerConfig":false,"required":true,"hideFromConsole":true,"name":"Act-On Callback URL","id":316420,"groupControl":false,"key":"oauth.callback.url"},{"internal":false,"companyConfig":false,"displayOrder":6,"active":true,"description":"Act-On API Key","type":"TEXTFIELD_128","resellerConfig":false,"required":true,"hideFromConsole":true,"name":"Act-On API Key","id":316421,"groupControl":false,"key":"oauth.api.key"},{"internal":false,"companyConfig":false,"displayOrder":7,"active":true,"description":"Act-On API Secret","type":"PASSWORD","resellerConfig":false,"required":true,"hideFromConsole":true,"name":"Act-On API Secret","id":316422,"groupControl":false,"key":"oauth.api.secret"},{"internal":true,"companyConfig":false,"displayOrder":8,"active":true,"description":"Act-On Token Type","type":"TEXTFIELD_128","resellerConfig":false,"required":true,"hideFromConsole":true,"name":"Act-On Token Type","id":316423,"groupControl":false,"key":"oauth.token_type"},{"internal":false,"companyConfig":false,"defaultValue":"true","displayOrder":51,"active":true,"description":"Used to enable/disable filtering of null values from the responses.","type":"BOOLEAN","resellerConfig":false,"required":false,"hideFromConsole":false,"name":"Filter null values from the response","id":316424,"groupControl":false,"key":"filter.response.nulls"},{"internal":false,"companyConfig":false,"displayOrder":98,"active":true,"description":"Generic map used to specify default fields for bulk download and GET /all requests. Each key should be the canonical objectName and values may be specified as a comma-delimited string or a list of strings","type":"TEXTAREA","resellerConfig":false,"required":false,"hideFromConsole":true,"name":"Default select fields","id":316425,"groupControl":false,"key":"default.select.fields.map"},{"internal":true,"companyConfig":false,"defaultValue":"polling","displayOrder":100,"active":true,"description":"Vendor Event Type","type":"TEXTFIELD_128","resellerConfig":false,"required":true,"hideFromConsole":true,"name":"Vendor Event Type","id":316427,"groupControl":false,"key":"event.vendor.type"},{"internal":false,"companyConfig":false,"defaultValue":"{\n  \"contacts\": {\n    \"url\": \"/hubs/marketing/lists/{listId}/contacts?where=modafter='${epoch}'\",\n    \"idField\": \"_contact_id_\",\n    \"datesConfiguration\": {\n      \"updatedDateField\": \"__modified_date\",\n      \"updatedDateFormat\": \"milliseconds\",\n      \"createdDateField\": \"__created_date\",\n      \"createdDateFormat\": \"milliseconds\"\n    }\n  }\n}","displayOrder":100,"active":true,"description":"Event Poller Resources Configuration","type":"TEXTAREA","resellerConfig":false,"required":true,"hideFromConsole":false,"name":"Event Poller Resources Configuration","id":316429,"groupControl":false,"key":"event.poller.configuration"},{"internal":false,"companyConfig":false,"displayOrder":100,"active":true,"description":"A key used to generate a validation hash header of the event/bulk notification webhook callback payload","type":"TEXTFIELD_128","resellerConfig":false,"required":false,"hideFromConsole":false,"name":"Callback Notification Signature Key","id":316431,"groupControl":false,"key":"event.notification.signature.key"},{"internal":false,"companyConfig":false,"displayOrder":100,"active":true,"description":"Event Notification Callback URL","type":"TEXTFIELD_128","resellerConfig":false,"required":false,"hideFromConsole":false,"name":"Event Notification Callback URL","id":316428,"groupControl":false,"key":"event.notification.callback.url"},{"internal":false,"companyConfig":false,"defaultValue":"15","displayOrder":100,"active":true,"description":"Event poller refresh interval","type":"TEXTFIELD_128","resellerConfig":false,"required":true,"hideFromConsole":false,"name":"Event poller refresh interval","id":316426,"groupControl":false,"key":"event.poller.refresh_interval"},{"internal":false,"companyConfig":false,"defaultValue":"false","displayOrder":100,"active":true,"description":"Enable/Disable Events","type":"BOOLEAN","resellerConfig":false,"required":true,"hideFromConsole":false,"name":"Enabled/Disable Event Notifications","id":316430,"groupControl":false,"key":"event.notification.enabled"},{"internal":false,"companyConfig":false,"displayOrder":110,"active":true,"description":"Event Notification basic authentication username","type":"TEXTFIELD_1000","resellerConfig":false,"required":false,"hideFromConsole":false,"name":"Event Notification Basic Authentication UserName","id":316432,"groupControl":false,"key":"event.notification.basic.username"},{"internal":false,"companyConfig":false,"displayOrder":112,"active":true,"description":"Event Notification basic authentication password","type":"PASSWORD","resellerConfig":false,"required":false,"hideFromConsole":false,"name":"Event Notification Basic Authentication Password","id":316433,"groupControl":false,"key":"event.notification.basic.password"},{"internal":true,"companyConfig":false,"displayOrder":300,"active":true,"description":"Event Notification Subscription ID","type":"TEXTFIELD_64","resellerConfig":false,"required":false,"hideFromConsole":true,"name":"Event Notification Subscription ID","id":316434,"groupControl":false,"key":"event.notification.subscription.id"}],"objects":[],"description":"Add an Act-On Instance to connect your existing Act-On account to the Marketing Hub, allowing you to manage campaigns, lists, leads etc. across multiple Marketing Elements. You will need your Act-On account information to add an instance.","cloneable":false,"extended":false,"hookName":"Act-On","bulkDownloadEnabled":true,"useModelsForMetadata":true,"defaultTransformations":[{"name":"listsContacts","vendorName":"contacts"},{"name":"contacts","vendorName":"contact"},{"name":"lists","vendorName":"list"},{"name":"optouts","vendorName":"optout"},{"name":"subscription-types","vendorName":"subscription-categories"}],"trialAccount":false,"logo":"acton","id":34500,"hooks":[],"beta":false,"key":"acton222","authentication":{"type":"oauth2"},"bulkUploadEnabled":true,"image":"elements/provider_acton.png","active":true,"resources":[{"method":"GET","kind":"eb","description":"Search for accounts","type":"api","vendorPath":"/accounts","path":"/hubs/marketing/accounts","createdDate":"2020-01-22T07:35:04Z","vendorMethod":"GET","response":{"contentType":"application/json"},"ownerAccountId":39667,"tryitoutDisable":false,"model":{"requestName":"accountsGetReq","transform":false,"name":"accountsGetRes","requestSwagger":{"accountsGetReq":{"title":"accountsGetReq","properties":{"id":{"x-samplevalue":123,"format":"int32","type":"integer"}}}},"swagger":{"accountsGetResObject":{"title":"accountsGetRes","type":"object","properties":{"id":{"x-samplevalue":123,"format":"int32","type":"integer"}}}}},"id":348461,"hooks":[],"parameters":[{"vendorType":"query","resourceId":348461,"converter":"toQueryParameters","dataType":"string","description":"The CEQL search expression, or the where clause, without the WHERE keyword. For example, to search for objects last modified on or after Oct 22, 2019\u2019, the search expression will be where=lastModifiedDate>=\u20192019-10-22T00:00:00.000Z","vendorDataType":"string","source":"request","type":"query","vendorName":"converter:toQueryParameters","required":false,"createdDate":"2020-01-22T07:35:04Z","name":"where","id":859788},{"vendorType":"query","resourceId":348461,"createdDate":"2020-01-22T07:35:04Z","dataType":"string","name":"fields","description":"Specify the fields to return in the response payload. Defaults to all standard fields","vendorDataType":"string","id":859787,"source":"request","type":"query","vendorName":"fields","required":false},{"vendorType":"query","resourceId":348461,"createdDate":"2020-01-22T07:35:04Z","dataType":"string","name":"orderBy","description":"The field(s) to order by. For example to order by firstname ascending use &#39;firstname asc&#39;","vendorDataType":"string","id":859786,"source":"request","type":"query","vendorName":"orderBy","required":false},{"vendorType":"query","resourceId":348461,"createdDate":"2020-01-22T07:35:04Z","dataType":"string","name":"limit","description":"The number of resources to return in a given page","vendorDataType":"number","id":859785,"source":"request","type":"query","vendorName":"limit","required":false},{"vendorType":"query","resourceId":348461,"createdDate":"2020-01-22T07:35:04Z","dataType":"string","name":"offset","description":"The number of resources to skip","vendorDataType":"number","id":859784,"source":"request","type":"query","vendorName":"offset","required":false},{"vendorType":"query","resourceId":348461,"createdDate":"2020-01-22T07:35:04Z","dataType":"string","name":"page","description":"The page number. Defaults to 1 if not provided","vendorDataType":"string","id":859783,"source":"request","type":"query","vendorName":"page","required":false},{"vendorType":"query","resourceId":348461,"createdDate":"2020-01-22T07:35:04Z","dataType":"string","name":"pageSize","description":"The page size. Defaults to 200 if not provided. Maximum of 2000","vendorDataType":"string","id":859782,"source":"request","type":"query","vendorName":"pageSize","required":false},{"vendorType":"query","resourceId":348461,"createdDate":"2020-01-22T07:35:04Z","dataType":"string","name":"nextPage","description":"The next page cursor, taken from the response header: elements-next-page-token","vendorDataType":"string","id":859781,"source":"request","type":"query","vendorName":"nextPage","required":false}]},{"method":"POST","kind":"eb","description":"Create a(n) accounts","type":"api","vendorPath":"/accounts","path":"/hubs/marketing/accounts","createdDate":"2020-01-22T07:35:04Z","vendorMethod":"POST","response":{"contentType":"application/json"},"ownerAccountId":39667,"tryitoutDisable":false,"model":{"requestName":"accountsPostReq","transform":false,"name":"accountsPostRes","requestSwagger":{"accountsPostReq":{"title":"accountsPostReq","type":"object","properties":{"id":{"x-samplevalue":123,"format":"int32","type":"integer"}}}},"swagger":{"accountsPostRes":{"title":"accountsPostRes","type":"object","properties":{"id":{"x-samplevalue":123,"format":"int32","type":"integer"}}}}},"id":348462,"hooks":[],"parameters":[{"vendorType":"body","resourceId":348462,"createdDate":"2020-01-22T07:35:04Z","dataType":"accountsPostReq","name":"body","description":"The accounts object body","vendorDataType":"accountsPostReq","id":859789,"source":"request","type":"body","vendorName":"body","required":true}]},{"method":"DELETE","kind":"eb","description":"Delete a(n) accounts","type":"api","vendorPath":"/accounts/{id}","path":"/hubs/marketing/accounts/{id}","createdDate":"2020-01-22T07:35:04Z","vendorMethod":"DELETE","response":{"contentType":"application/json"},"ownerAccountId":39667,"tryitoutDisable":false,"model":{"requestName":"accountsDeleteReq","transform":false,"name":"accountsDeleteRes","requestSwagger":{"accountsDeleteReq":{"title":"accountsDeleteReq","properties":{"id":{"x-samplevalue":123,"format":"int32","type":"integer"}}}},"swagger":{"accountsDeleteRes":{"title":"accountsDeleteRes","type":"object","properties":{"id":{"x-samplevalue":123,"format":"int32","type":"integer"}}}}},"id":348466,"hooks":[],"parameters":[{"vendorType":"path","resourceId":348466,"createdDate":"2020-01-22T07:35:04Z","dataType":"string","name":"id","description":"The accounts ID","vendorDataType":"string","id":859795,"source":"request","type":"path","vendorName":"id","required":true}]},{"method":"GET","kind":"eb","description":"Retrieve a(n) accounts","type":"api","vendorPath":"/accounts/{id}","path":"/hubs/marketing/accounts/{id}","createdDate":"2020-01-22T07:35:04Z","vendorMethod":"GET","response":{"contentType":"application/json"},"ownerAccountId":39667,"tryitoutDisable":false,"model":{"requestName":"accountsGetByIdReq","transform":false,"name":"accountsGetByIdRes","requestSwagger":{"accountsGetByIdReq":{"title":"accountsGetByIdReq","properties":{"id":{"x-samplevalue":123,"format":"int32","type":"integer"}}}},"swagger":{"accountsGetByIdRes":{"title":"accountsGetByIdRes","type":"object","properties":{"id":{"x-samplevalue":123,"format":"int32","type":"integer"}}}}},"id":348463,"hooks":[],"parameters":[{"vendorType":"path","resourceId":348463,"createdDate":"2020-01-22T07:35:04Z","dataType":"string","name":"id","description":"The accounts ID","vendorDataType":"string","id":859790,"source":"request","type":"path","vendorName":"id","required":true}]},{"method":"PATCH","kind":"eb","description":"Update a(n) accounts","type":"api","vendorPath":"/accounts/{id}","path":"/hubs/marketing/accounts/{id}","createdDate":"2020-01-22T07:35:04Z","vendorMethod":"PATCH","response":{"contentType":"application/json"},"ownerAccountId":39667,"tryitoutDisable":false,"model":{"requestName":"accountsPatchReq","transform":false,"name":"accountsPatchRes","requestSwagger":{"accountsPatchReq":{"title":"accountsPatchReq","type":"object","properties":{"id":{"x-samplevalue":123,"format":"int32","type":"integer"}}}},"swagger":{"accountsPatchRes":{"title":"accountsPatchRes","type":"object","properties":{"id":{"x-samplevalue":123,"format":"int32","type":"integer"}}}}},"id":348464,"hooks":[],"parameters":[{"vendorType":"body","resourceId":348464,"createdDate":"2020-01-22T07:35:04Z","dataType":"accountsPatchReq","name":"body","description":"The accounts object body","vendorDataType":"accountsPatchReq","id":859792,"source":"request","type":"body","vendorName":"body","required":true},{"vendorType":"path","resourceId":348464,"createdDate":"2020-01-22T07:35:04Z","dataType":"string","name":"id","description":"The accounts ID","vendorDataType":"string","id":859791,"source":"request","type":"path","vendorName":"id","required":true}]},{"method":"PUT","kind":"eb","description":"Update a(n) accounts","type":"api","vendorPath":"/accounts/{id}","path":"/hubs/marketing/accounts/{id}","createdDate":"2020-01-22T07:35:04Z","vendorMethod":"PUT","response":{"contentType":"application/json"},"ownerAccountId":39667,"tryitoutDisable":false,"model":{"requestName":"accountsPutReq","transform":false,"name":"accountsPutRes","requestSwagger":{"accountsPutReq":{"title":"accountsPutReq","type":"object","properties":{"id":{"x-samplevalue":123,"format":"int32","type":"integer"}}}},"swagger":{"accountsPutRes":{"title":"accountsPutRes","type":"object","properties":{"id":{"x-samplevalue":123,"format":"int32","type":"integer"}}}}},"id":348465,"hooks":[],"parameters":[{"vendorType":"body","resourceId":348465,"createdDate":"2020-01-22T07:35:04Z","dataType":"accountsPutReq","name":"body","description":"The accounts object body","vendorDataType":"accountsPutReq","id":859794,"source":"request","type":"body","vendorName":"body","required":true},{"vendorType":"path","resourceId":348465,"createdDate":"2020-01-22T07:35:04Z","dataType":"string","name":"id","description":"The accounts ID","vendorDataType":"string","id":859793,"source":"request","type":"path","vendorName":"id","required":true}]}],"protocolType":"http","transformationsEnabled":true,"deleted":false,"hub":"marketing","configDescription":"If you do not have a Act-On account, you can create one at <a href=\"http://www.act-on.com/\" target=\"_blank\">Act-On\n  Signup<\/a>","typeOauth":false,"name":"Act-On","extendable":true,"parameters":[{"elementId":34500,"vendorType":"header","createdDate":"2019-12-19T08:38:59Z","name":"application/json","id":17643,"source":"request","updatedDate":"2020-01-22T07:35:04Z","type":"value","vendorName":"Accept","required":false},{"elementId":34500,"vendorType":"header","createdDate":"2019-12-19T08:38:59Z","name":"application/json","id":17642,"source":"request","updatedDate":"2020-01-22T07:35:04Z","type":"value","vendorName":"Content-Type","required":false}]}